Project_dataset/__init__.py
Project_dataset/__version__.py
Project_dataset/core.py
project_dataset-1.0.dist-info/LICENSE
project_dataset-1.0.dist-info/METADATA
project_dataset-1.0.dist-info/WHEEL
project_dataset-1.0.dist-info/top_level.txt
project_dataset-1.0.dist-info/RECORD
