Metadata-Version: 2.1
Name: project-dataset
Version: 1.0
Summary: Dataset of our project
Home-page: https://github.com/Burlinlove/Project_dataset
Author: Burlin
Author-email: wang123hengsuan@gmail.com
License: MIT
Platform: UNKNOWN
Classifier: License :: OSI Approved :: MIT License
Classifier: Programming Language :: Python
Classifier: Programming Language :: Python :: 3
Classifier: Programming Language :: Python :: 3.6
Classifier: Programming Language :: Python :: Implementation :: CPython
Classifier: Programming Language :: Python :: Implementation :: PyPy
Requires-Python: >=3.6.0
